aliyunsdknlp_automl/__init__.py
aliyunsdknlp_automl/endpoint.py
aliyunsdknlp_automl/request/__init__.py
aliyunsdknlp_automl/request/v20191111/CreateAsyncPredictRequest.py
aliyunsdknlp_automl/request/v20191111/FindUserReport4AlinlpRequest.py
aliyunsdknlp_automl/request/v20191111/GetAsyncPredictRequest.py
aliyunsdknlp_automl/request/v20191111/GetPredictResultHighRequest.py
aliyunsdknlp_automl/request/v20191111/GetPredictResultRequest.py
aliyunsdknlp_automl/request/v20191111/RunPreTrainServiceNewRequest.py
aliyunsdknlp_automl/request/v20191111/RunPreTrainServiceRequest.py
aliyunsdknlp_automl/request/v20191111/__init__.py
aliyun_python_sdk_nlp_automl-0.0.15.dist-info/LICENSE
aliyun_python_sdk_nlp_automl-0.0.15.dist-info/METADATA
aliyun_python_sdk_nlp_automl-0.0.15.dist-info/WHEEL
aliyun_python_sdk_nlp_automl-0.0.15.dist-info/top_level.txt
aliyun_python_sdk_nlp_automl-0.0.15.dist-info/RECORD
